rlieh_satlight/__init__.py
rlieh_satlight/core.py
rlieh_satlight-0.0.4.dist-info/COPYING.md
rlieh_satlight-0.0.4.dist-info/METADATA
rlieh_satlight-0.0.4.dist-info/WHEEL
rlieh_satlight-0.0.4.dist-info/entry_points.txt
rlieh_satlight-0.0.4.dist-info/top_level.txt
rlieh_satlight-0.0.4.dist-info/RECORD
