Metadata-Version: 2.1
Name: rlieh-satlight
Version: 0.0.4
Summary: This module provides an interface to manage light phases using .ini file to perform remote call to a RLIEH satellite
Home-page: http://github.com/owatte/rlieh-satlight
Author: Olivier Watté - RLIEH project by Biolo.tech
Author-email: owatte@biolo.tech
License: UNKNOWN
Platform: UNKNOWN
Classifier: Programming Language :: Python
Classifier: Development Status :: 3 - Alpha
Classifier: Environment :: Console
Classifier: License :: OSI Approved :: GNU General Public License v3 or later (GPLv3+)
Classifier: Intended Audience :: Science/Research
Classifier: Natural Language :: English
Classifier: Operating System :: OS Independent
Classifier: Programming Language :: Python :: 3
Classifier: Topic :: Scientific/Engineering
Requires-Dist: argparse
Requires-Dist: configparser
Requires-Dist: requests
